Metadata-Version: 2.1
Name: nb2plots
Version: 0.6.1
Summary: Converting between ipython notebooks and sphinx docs
Home-page: http://github.com/matthew-brett/nb2plots
Author: Matthew Brett
Author-email: matthew.brett@gmail.com
Maintainer: Matthew Brett
Maintainer-email: matthew.brett@gmail.com
License: BSD license
Platform: UNKNOWN
Classifier: Development Status :: 2 - Pre-Alpha
Classifier: Environment :: Console
Classifier: Intended Audience :: Developers
Classifier: Intended Audience :: Science/Research
Classifier: License :: OSI Approved :: BSD License
Classifier: Programming Language :: Python
Classifier: Programming Language :: Python :: 3
Classifier: Topic :: Scientific/Engineering
Classifier: Operating System :: Microsoft :: Windows
Classifier: Operating System :: POSIX
Classifier: Operating System :: Unix
Classifier: Operating System :: MacOS
License-File: LICENSE
Requires-Dist: ipython[notebook] (>=4.0)
Requires-Dist: sphinx (>=1.4)
Requires-Dist: numpy (>=1.7.1)
Requires-Dist: matplotlib (>=2.0)
Requires-Dist: six (>=1.10)
Requires-Dist: sphinxtesters (>=0.2)
Requires-Dist: texext
Provides-Extra: test
Requires-Dist: pytest ; extra == 'test'
Requires-Dist: mock ; extra == 'test'
Requires-Dist: scripttester ; extra == 'test'
